keycloak/__init__.py
keycloak/_version.py
keycloak/connection.py
keycloak/exceptions.py
keycloak/keycloak_admin.py
keycloak/keycloak_openid.py
keycloak/urls_patterns.py
adamatics_keycloak-2.2.0.dist-info/LICENSE
adamatics_keycloak-2.2.0.dist-info/METADATA
adamatics_keycloak-2.2.0.dist-info/WHEEL
adamatics_keycloak-2.2.0.dist-info/top_level.txt
adamatics_keycloak-2.2.0.dist-info/RECORD
