Metadata-Version: 2.1
Name: adamatics-keycloak
Version: 2.2.0
Summary: adamatics-keycloak is a Python package providing access to the Keycloak API, forked from the python-keycloak package.
Home-page: https://github.com/adamatics/adamatics-keycloak
Author: Marcos Pereira, Richard Nemeth
Author-email: ryshoooo@gmail.com
License: The MIT License
Project-URL: Documentation, https://adamatics-keycloak.readthedocs.io/en/latest/
Project-URL: Issue tracker, https://github.com/adamatics/adamatics-keycloak/issues
Keywords: keycloak openid oidc
Platform: UNKNOWN
Classifier: Programming Language :: Python :: 3
Classifier: License :: OSI Approved :: MIT License
Classifier: Development Status :: 3 - Alpha
Classifier: Operating System :: MacOS
Classifier: Operating System :: Unix
Classifier: Operating System :: Microsoft :: Windows
Classifier: Topic :: Utilities
Requires-Python: >=3.7
License-File: LICENSE
Requires-Dist: requests (>=2.20.0)
Requires-Dist: python-jose (>=1.4.0)
Requires-Dist: urllib3 (>=1.26.0)
Provides-Extra: docs
Requires-Dist: mock ; extra == 'docs'
Requires-Dist: alabaster ; extra == 'docs'
Requires-Dist: commonmark ; extra == 'docs'
Requires-Dist: recommonmark ; extra == 'docs'
Requires-Dist: sphinx ; extra == 'docs'
Requires-Dist: sphinx-rtd-theme ; extra == 'docs'
Requires-Dist: readthedocs-sphinx-ext ; extra == 'docs'
Requires-Dist: m2r2 ; extra == 'docs'
Requires-Dist: sphinx-autoapi ; extra == 'docs'
